procmanager/__init__.py
procmanager-1.0.6.dist-info/entry_points.txt
procmanager-1.0.6.dist-info/WHEEL
procmanager-1.0.6.dist-info/METADATA
procmanager-1.0.6.dist-info/RECORD
