Metadata-Version: 2.1
Name: procmanager
Version: 1.0.6
Summary: Helps starting & stopping programs
License: MIT
Author: fdev31
Author-email: fdev31@gmail.com
Requires-Python: >=3.10,<4.0
Classifier: License :: OSI Approved :: MIT License
Classifier: Programming Language :: Python :: 3
Classifier: Programming Language :: Python :: 3.10
